odoo8_addon_procurement_analytic-8.0.1.0.0.99.dev20-py2.7-nspkg.pth
odoo8_addon_procurement_analytic-8.0.1.0.0.99.dev20.dist-info/DESCRIPTION.rst
odoo8_addon_procurement_analytic-8.0.1.0.0.99.dev20.dist-info/METADATA
odoo8_addon_procurement_analytic-8.0.1.0.0.99.dev20.dist-info/RECORD
odoo8_addon_procurement_analytic-8.0.1.0.0.99.dev20.dist-info/WHEEL
odoo8_addon_procurement_analytic-8.0.1.0.0.99.dev20.dist-info/metadata.json
odoo8_addon_procurement_analytic-8.0.1.0.0.99.dev20.dist-info/namespace_packages.txt
odoo8_addon_procurement_analytic-8.0.1.0.0.99.dev20.dist-info/top_level.txt
odoo_addons/procurement_analytic/README.rst
odoo_addons/procurement_analytic/__init__.py
odoo_addons/procurement_analytic/__openerp__.py
odoo_addons/procurement_analytic/i18n/ca.po
odoo_addons/procurement_analytic/i18n/de.po
odoo_addons/procurement_analytic/i18n/el_GR.po
odoo_addons/procurement_analytic/i18n/es.po
odoo_addons/procurement_analytic/i18n/es_MX.po
odoo_addons/procurement_analytic/i18n/fi.po
odoo_addons/procurement_analytic/i18n/fr.po
odoo_addons/procurement_analytic/i18n/hr.po
odoo_addons/procurement_analytic/i18n/it.po
odoo_addons/procurement_analytic/i18n/procurement_analytic.pot
odoo_addons/procurement_analytic/i18n/pt_BR.po
odoo_addons/procurement_analytic/i18n/pt_PT.po
odoo_addons/procurement_analytic/i18n/ro.po
odoo_addons/procurement_analytic/i18n/sk.po
odoo_addons/procurement_analytic/i18n/sk_SK.po
odoo_addons/procurement_analytic/i18n/sl.po
odoo_addons/procurement_analytic/i18n/tr_TR.po
odoo_addons/procurement_analytic/i18n/zh_CN.po
odoo_addons/procurement_analytic/models/__init__.py
odoo_addons/procurement_analytic/models/procurement.py
odoo_addons/procurement_analytic/static/description/icon.png
odoo_addons/procurement_analytic/views/procurement_analytic.xml
